setup.cfg
setup.py
django_social_followers/__init__.py
django_social_followers/social.py
django_social_followers.egg-info/PKG-INFO
django_social_followers.egg-info/SOURCES.txt
django_social_followers.egg-info/dependency_links.txt
django_social_followers.egg-info/requires.txt
django_social_followers.egg-info/top_level.txt