Metadata-Version: 1.1
Name: django-social-followers
Version: 0.7
Summary: Get followers from Social Media channels
Home-page: https://github.com/willandskill/django_social_followers
Author: Will And Skill AB - Sweden
Author-email: info@willandskill.se
License: UNKNOWN
Download-URL: https://github.com/willandskill/django_social_followers/releases/tag/0.7
Keywords: social,followers,instagram,facebook,twitter
Platform: UNKNOWN
